{
	"$schema": "http://schema.management.azure.com/schemas/2015-01-01/deploymentTemplate.json#",
	"contentVersion": "1.0.0.0",
	"parameters": {
		"factoryName": {
			"type": "string",
			"metadata": "Data Factory name",
			"defaultValue": "ADF-Manu-Bootcamp"
		}
	},
	"variables": {
		"factoryId": "[concat('Microsoft.DataFactory/factories/', parameters('factoryName'))]"
	},
	"resources": [
		{
			"name": "[concat(parameters('factoryName'), '/worldcup_group_sql')]",
			"type": "Microsoft.DataFactory/factories/datasets",
			"apiVersion": "2018-06-01",
			"properties": {
				"linkedServiceName": {
					"referenceName": "AzureSqlDatabase1",
					"type": "LinkedServiceReference"
				},
				"annotations": [],
				"type": "AzureSqlTable",
				"schema": [
					{
						"name": "Groups",
						"type": "varchar"
					},
					{
						"name": "Team",
						"type": "varchar"
					},
					{
						"name": "FIFA_Ranking",
						"type": "int",
						"precision": 10
					}
				],
				"typeProperties": {
					"schema": "stage",
					"table": "world_cup_groups"
				}
			},
			"dependsOn": []
		},
		{
			"name": "[concat(parameters('factoryName'), '/worldcup_matches_2022')]",
			"type": "Microsoft.DataFactory/factories/datasets",
			"apiVersion": "2018-06-01",
			"properties": {
				"linkedServiceName": {
					"referenceName": "AzureDataLakeStorageManu",
					"type": "LinkedServiceReference"
				},
				"annotations": [],
				"type": "DelimitedText",
				"typeProperties": {
					"location": {
						"type": "AzureBlobFSLocation",
						"fileName": "2022_world_cup_matches.csv",
						"folderPath": "worldcup",
						"fileSystem": "bootcampcontainer"
					},
					"columnDelimiter": ",",
					"escapeChar": "\\",
					"firstRowAsHeader": true,
					"quoteChar": "\""
				},
				"schema": [
					{
						"name": "ID",
						"type": "String"
					},
					{
						"name": "Year",
						"type": "String"
					},
					{
						"name": "Date",
						"type": "String"
					},
					{
						"name": "Stage",
						"type": "String"
					},
					{
						"name": "Home Team",
						"type": "String"
					},
					{
						"name": "Away Team",
						"type": "String"
					},
					{
						"name": "Host Team",
						"type": "String"
					}
				]
			},
			"dependsOn": []
		},
		{
			"name": "[concat(parameters('factoryName'), '/worldcup_squad_2022')]",
			"type": "Microsoft.DataFactory/factories/datasets",
			"apiVersion": "2018-06-01",
			"properties": {
				"linkedServiceName": {
					"referenceName": "AzureDataLakeStorageManu",
					"type": "LinkedServiceReference"
				},
				"annotations": [],
				"type": "DelimitedText",
				"typeProperties": {
					"location": {
						"type": "AzureBlobFSLocation",
						"fileName": "2022_world_cup_squads.csv",
						"folderPath": "worldcup",
						"fileSystem": "bootcampcontainer"
					},
					"columnDelimiter": ",",
					"escapeChar": "\\",
					"firstRowAsHeader": true,
					"quoteChar": "\""
				},
				"schema": [
					{
						"name": "ID",
						"type": "String"
					},
					{
						"name": "Team",
						"type": "String"
					},
					{
						"name": "Position",
						"type": "String"
					},
					{
						"name": "Player",
						"type": "String"
					},
					{
						"name": "Age",
						"type": "String"
					},
					{
						"name": "Caps",
						"type": "String"
					},
					{
						"name": "Goals",
						"type": "String"
					},
					{
						"name": "WC Goals",
						"type": "String"
					},
					{
						"name": "League",
						"type": "String"
					},
					{
						"name": "Club",
						"type": "String"
					}
				]
			},
			"dependsOn": []
		},
		{
			"name": "[concat(parameters('factoryName'), '/worldcup_squad_sql')]",
			"type": "Microsoft.DataFactory/factories/datasets",
			"apiVersion": "2018-06-01",
			"properties": {
				"linkedServiceName": {
					"referenceName": "AzureSqlDatabase1",
					"type": "LinkedServiceReference"
				},
				"annotations": [],
				"type": "AzureSqlTable",
				"schema": [
					{
						"name": "ID",
						"type": "int",
						"precision": 10
					},
					{
						"name": "Team",
						"type": "varchar"
					},
					{
						"name": "Position",
						"type": "varchar"
					},
					{
						"name": "Player",
						"type": "varchar"
					},
					{
						"name": "Age",
						"type": "int",
						"precision": 10
					},
					{
						"name": "Caps",
						"type": "int",
						"precision": 10
					},
					{
						"name": "Goals",
						"type": "int",
						"precision": 10
					},
					{
						"name": "WC_Goals",
						"type": "int",
						"precision": 10
					},
					{
						"name": "League",
						"type": "varchar"
					},
					{
						"name": "Club",
						"type": "varchar"
					}
				],
				"typeProperties": {
					"schema": "stage",
					"table": "world_cup_squads"
				}
			},
			"dependsOn": []
		},
		{
			"name": "[concat(parameters('factoryName'), '/worldcupmatches')]",
			"type": "Microsoft.DataFactory/factories/datasets",
			"apiVersion": "2018-06-01",
			"properties": {
				"linkedServiceName": {
					"referenceName": "AzureDataLakeStorageManu",
					"type": "LinkedServiceReference"
				},
				"annotations": [],
				"type": "DelimitedText",
				"typeProperties": {
					"location": {
						"type": "AzureBlobFSLocation",
						"fileName": "world_cup_matches.csv",
						"folderPath": "worldcup",
						"fileSystem": "bootcampcontainer"
					},
					"columnDelimiter": ",",
					"escapeChar": "\\",
					"firstRowAsHeader": true,
					"quoteChar": "\""
				},
				"schema": [
					{
						"name": "ID",
						"type": "String"
					},
					{
						"name": "Year",
						"type": "String"
					},
					{
						"name": "Date",
						"type": "String"
					},
					{
						"name": "Stage",
						"type": "String"
					},
					{
						"name": "Home Team",
						"type": "String"
					},
					{
						"name": "Home Goals",
						"type": "String"
					},
					{
						"name": "Away Goals",
						"type": "String"
					},
					{
						"name": "Away Team",
						"type": "String"
					},
					{
						"name": "Win Conditions",
						"type": "String"
					},
					{
						"name": "Host Team",
						"type": "String"
					}
				]
			},
			"dependsOn": []
		},
		{
			"name": "[concat(parameters('factoryName'), '/CopyCsvToDB')]",
			"type": "Microsoft.DataFactory/factories/pipelines",
			"apiVersion": "2018-06-01",
			"properties": {
				"activities": [
					{
						"name": "Copy Employee",
						"type": "Copy",
						"dependsOn": [],
						"policy": {
							"timeout": "0.12:00:00",
							"retry": 0,
							"retryIntervalInSeconds": 30,
							"secureOutput": false,
							"secureInput": false
						},
						"userProperties": [],
						"typeProperties": {
							"source": {
								"type": "DelimitedTextSource",
								"storeSettings": {
									"type": "AzureBlobFSReadSettings",
									"recursive": true,
									"enablePartitionDiscovery": false
								},
								"formatSettings": {
									"type": "DelimitedTextReadSettings"
								}
							},
							"sink": {
								"type": "AzureSqlSink",
								"writeBehavior": "insert",
								"sqlWriterUseTableLock": false
							},
							"enableStaging": false,
							"translator": {
								"type": "TabularTranslator",
								"mappings": [
									{
										"source": {
											"name": "EmpId",
											"type": "String",
											"physicalType": "String"
										},
										"sink": {
											"name": "EmpId",
											"type": "Int32",
											"physicalType": "int"
										}
									},
									{
										"source": {
											"name": "Name",
											"type": "String",
											"physicalType": "String"
										},
										"sink": {
											"name": "Name",
											"type": "String",
											"physicalType": "varchar"
										}
									},
									{
										"source": {
											"name": "Address",
											"type": "String",
											"physicalType": "String"
										},
										"sink": {
											"name": "Address",
											"type": "String",
											"physicalType": "varchar"
										}
									},
									{
										"source": {
											"name": "Mobile ",
											"type": "String",
											"physicalType": "String"
										},
										"sink": {
											"name": "Mobile",
											"type": "String",
											"physicalType": "varchar"
										}
									}
								],
								"typeConversion": true,
								"typeConversionSettings": {
									"allowDataTruncation": true,
									"treatBooleanAsNumber": false
								}
							}
						},
						"inputs": [
							{
								"referenceName": "tblEmployeeFile",
								"type": "DatasetReference",
								"parameters": {}
							}
						],
						"outputs": [
							{
								"referenceName": "AzureSqlTable1",
								"type": "DatasetReference",
								"parameters": {}
							}
						]
					},
					{
						"name": "Copy EmpSalary",
						"type": "Copy",
						"dependsOn": [
							{
								"activity": "Copy Employee",
								"dependencyConditions": [
									"Succeeded"
								]
							}
						],
						"policy": {
							"timeout": "0.12:00:00",
							"retry": 0,
							"retryIntervalInSeconds": 30,
							"secureOutput": false,
							"secureInput": false
						},
						"userProperties": [],
						"typeProperties": {
							"source": {
								"type": "DelimitedTextSource",
								"storeSettings": {
									"type": "AzureBlobFSReadSettings",
									"recursive": true,
									"enablePartitionDiscovery": false
								},
								"formatSettings": {
									"type": "DelimitedTextReadSettings"
								}
							},
							"sink": {
								"type": "AzureSqlSink",
								"writeBehavior": "insert",
								"sqlWriterUseTableLock": false
							},
							"enableStaging": false,
							"translator": {
								"type": "TabularTranslator",
								"mappings": [
									{
										"source": {
											"name": "EmpId ",
											"type": "String",
											"physicalType": "String"
										},
										"sink": {
											"name": "EmpId",
											"type": "Int32",
											"physicalType": "int"
										}
									},
									{
										"source": {
											"name": "Month",
											"type": "String",
											"physicalType": "String"
										},
										"sink": {
											"name": "Month",
											"type": "String",
											"physicalType": "varchar"
										}
									},
									{
										"source": {
											"name": "Salary ",
											"type": "String",
											"physicalType": "String"
										},
										"sink": {
											"name": "Salary",
											"type": "Double",
											"physicalType": "float"
										}
									}
								],
								"typeConversion": true,
								"typeConversionSettings": {
									"allowDataTruncation": true,
									"treatBooleanAsNumber": false
								}
							}
						},
						"inputs": [
							{
								"referenceName": "tblSalaryFile",
								"type": "DatasetReference",
								"parameters": {}
							}
						],
						"outputs": [
							{
								"referenceName": "AzureSqlTable2",
								"type": "DatasetReference",
								"parameters": {}
							}
						]
					},
					{
						"name": "SpEmpSalaryDetails",
						"type": "SqlServerStoredProcedure",
						"dependsOn": [
							{
								"activity": "Copy EmpSalary",
								"dependencyConditions": [
									"Succeeded"
								]
							}
						],
						"policy": {
							"timeout": "0.12:00:00",
							"retry": 0,
							"retryIntervalInSeconds": 30,
							"secureOutput": false,
							"secureInput": false
						},
						"userProperties": [],
						"typeProperties": {
							"storedProcedureName": "[[dbo].[spEmpSalaryDetails]"
						},
						"linkedServiceName": {
							"referenceName": "AzureSqlDatabaseManu",
							"type": "LinkedServiceReference"
						}
					}
				],
				"policy": {
					"elapsedTimeMetric": {},
					"cancelAfter": {}
				},
				"annotations": [],
				"lastPublishTime": "2023-06-19T06:15:59Z"
			},
			"dependsOn": []
		},
		{
			"name": "[concat(parameters('factoryName'), '/CopyDbToCSV')]",
			"type": "Microsoft.DataFactory/factories/pipelines",
			"apiVersion": "2018-06-01",
			"properties": {
				"activities": [
					{
						"name": "Copy TblEmpSalaryReport",
						"type": "Copy",
						"dependsOn": [],
						"policy": {
							"timeout": "0.12:00:00",
							"retry": 0,
							"retryIntervalInSeconds": 30,
							"secureOutput": false,
							"secureInput": false
						},
						"userProperties": [],
						"typeProperties": {
							"source": {
								"type": "AzureSqlSource",
								"queryTimeout": "02:00:00",
								"partitionOption": "None"
							},
							"sink": {
								"type": "DelimitedTextSink",
								"storeSettings": {
									"type": "AzureBlobFSWriteSettings"
								},
								"formatSettings": {
									"type": "DelimitedTextWriteSettings",
									"quoteAllText": true,
									"fileExtension": ".txt"
								}
							},
							"enableStaging": false,
							"translator": {
								"type": "TabularTranslator",
								"mappings": [
									{
										"source": {
											"name": "Name",
											"type": "String",
											"physicalType": "varchar"
										},
										"sink": {
											"name": "Name",
											"type": "String",
											"physicalType": "String"
										}
									},
									{
										"source": {
											"name": "Address",
											"type": "String",
											"physicalType": "varchar"
										},
										"sink": {
											"name": "Address",
											"type": "String",
											"physicalType": "String"
										}
									},
									{
										"source": {
											"name": "Mobile",
											"type": "String",
											"physicalType": "varchar"
										},
										"sink": {
											"name": "Mobile",
											"type": "String",
											"physicalType": "String"
										}
									},
									{
										"source": {
											"name": "Month",
											"type": "String",
											"physicalType": "varchar"
										},
										"sink": {
											"name": "Month",
											"type": "String",
											"physicalType": "String"
										}
									},
									{
										"source": {
											"name": "Salary",
											"type": "Double",
											"physicalType": "float"
										},
										"sink": {
											"name": "Salary",
											"type": "String",
											"physicalType": "String"
										}
									}
								],
								"typeConversion": true,
								"typeConversionSettings": {
									"allowDataTruncation": true,
									"treatBooleanAsNumber": false
								}
							}
						},
						"inputs": [
							{
								"referenceName": "TblEmpSalaryReport",
								"type": "DatasetReference",
								"parameters": {}
							}
						],
						"outputs": [
							{
								"referenceName": "tblEmpSalaryReportFile",
								"type": "DatasetReference",
								"parameters": {}
							}
						]
					}
				],
				"policy": {
					"elapsedTimeMetric": {},
					"cancelAfter": {}
				},
				"annotations": [],
				"lastPublishTime": "2023-06-19T06:17:15Z"
			},
			"dependsOn": []
		},
		{
			"name": "[concat(parameters('factoryName'), '/PizzaSales')]",
			"type": "Microsoft.DataFactory/factories/pipelines",
			"apiVersion": "2018-06-01",
			"properties": {
				"activities": [
					{
						"name": "Copy data1",
						"type": "Copy",
						"dependsOn": [],
						"policy": {
							"timeout": "0.12:00:00",
							"retry": 0,
							"retryIntervalInSeconds": 30,
							"secureOutput": false,
							"secureInput": false
						},
						"userProperties": [],
						"typeProperties": {
							"source": {
								"type": "DelimitedTextSource",
								"storeSettings": {
									"type": "AzureBlobFSReadSettings",
									"recursive": true,
									"enablePartitionDiscovery": false
								},
								"formatSettings": {
									"type": "DelimitedTextReadSettings"
								}
							},
							"sink": {
								"type": "ParquetSink",
								"storeSettings": {
									"type": "AzureBlobFSWriteSettings"
								},
								"formatSettings": {
									"type": "ParquetWriteSettings"
								}
							},
							"enableStaging": false,
							"translator": {
								"type": "TabularTranslator",
								"typeConversion": true,
								"typeConversionSettings": {
									"allowDataTruncation": true,
									"treatBooleanAsNumber": false
								}
							}
						},
						"inputs": [
							{
								"referenceName": "DelimitedText1",
								"type": "DatasetReference",
								"parameters": {}
							}
						],
						"outputs": [
							{
								"referenceName": "Parquet1",
								"type": "DatasetReference",
								"parameters": {}
							}
						]
					}
				],
				"policy": {
					"elapsedTimeMetric": {},
					"cancelAfter": {}
				},
				"annotations": [],
				"lastPublishTime": "2023-07-08T16:19:58Z"
			},
			"dependsOn": []
		},
		{
			"name": "[concat(parameters('factoryName'), '/Worldcup_stagetable_load')]",
			"type": "Microsoft.DataFactory/factories/pipelines",
			"apiVersion": "2018-06-01",
			"properties": {
				"activities": [
					{
						"name": "Copy Worldcups to Stage",
						"type": "Copy",
						"dependsOn": [],
						"policy": {
							"timeout": "0.12:00:00",
							"retry": 0,
							"retryIntervalInSeconds": 30,
							"secureOutput": false,
							"secureInput": false
						},
						"userProperties": [],
						"typeProperties": {
							"source": {
								"type": "DelimitedTextSource",
								"storeSettings": {
									"type": "AzureBlobFSReadSettings",
									"recursive": true,
									"enablePartitionDiscovery": false
								},
								"formatSettings": {
									"type": "DelimitedTextReadSettings"
								}
							},
							"sink": {
								"type": "AzureSqlSink",
								"writeBehavior": "insert",
								"sqlWriterUseTableLock": false,
								"disableMetricsCollection": false
							},
							"enableStaging": false,
							"translator": {
								"type": "TabularTranslator",
								"mappings": [
									{
										"source": {
											"name": "Year",
											"type": "String",
											"physicalType": "String"
										},
										"sink": {
											"name": "Year",
											"type": "Int32",
											"physicalType": "int"
										}
									},
									{
										"source": {
											"name": "Host Country",
											"type": "String",
											"physicalType": "String"
										},
										"sink": {
											"name": "Host_Country",
											"type": "String",
											"physicalType": "varchar"
										}
									},
									{
										"source": {
											"name": "Winner",
											"type": "String",
											"physicalType": "String"
										},
										"sink": {
											"name": "Winner",
											"type": "String",
											"physicalType": "varchar"
										}
									},
									{
										"source": {
											"name": "Runners-Up",
											"type": "String",
											"physicalType": "String"
										},
										"sink": {
											"name": "Runners_Up",
											"type": "String",
											"physicalType": "varchar"
										}
									},
									{
										"source": {
											"name": "Third",
											"type": "String",
											"physicalType": "String"
										},
										"sink": {
											"name": "Third",
											"type": "String",
											"physicalType": "varchar"
										}
									},
									{
										"source": {
											"name": "Fourth",
											"type": "String",
											"physicalType": "String"
										},
										"sink": {
											"name": "Fourth",
											"type": "String",
											"physicalType": "varchar"
										}
									},
									{
										"source": {
											"name": "Goals Scored",
											"type": "String",
											"physicalType": "String"
										},
										"sink": {
											"name": "Goals_Scored",
											"type": "Int32",
											"physicalType": "int"
										}
									},
									{
										"source": {
											"name": "Qualified Teams",
											"type": "String",
											"physicalType": "String"
										},
										"sink": {
											"name": "Qualified_Teams",
											"type": "Int32",
											"physicalType": "int"
										}
									},
									{
										"source": {
											"name": "Matches Played",
											"type": "String",
											"physicalType": "String"
										},
										"sink": {
											"name": "Matches_Played",
											"type": "Int32",
											"physicalType": "int"
										}
									}
								],
								"typeConversion": true,
								"typeConversionSettings": {
									"allowDataTruncation": true,
									"treatBooleanAsNumber": false
								}
							}
						},
						"inputs": [
							{
								"referenceName": "WorldCup_csv",
								"type": "DatasetReference",
								"parameters": {}
							}
						],
						"outputs": [
							{
								"referenceName": "StageWorldcups",
								"type": "DatasetReference",
								"parameters": {}
							}
						]
					},
					{
						"name": "Copy worldcup matches to stage",
						"type": "Copy",
						"dependsOn": [
							{
								"activity": "Copy Worldcups to Stage",
								"dependencyConditions": [
									"Succeeded"
								]
							}
						],
						"policy": {
							"timeout": "0.12:00:00",
							"retry": 0,
							"retryIntervalInSeconds": 30,
							"secureOutput": false,
							"secureInput": false
						},
						"userProperties": [],
						"typeProperties": {
							"source": {
								"type": "DelimitedTextSource",
								"storeSettings": {
									"type": "AzureBlobFSReadSettings",
									"recursive": true,
									"enablePartitionDiscovery": false
								},
								"formatSettings": {
									"type": "DelimitedTextReadSettings"
								}
							},
							"sink": {
								"type": "AzureSqlSink",
								"writeBehavior": "insert",
								"sqlWriterUseTableLock": false
							},
							"enableStaging": false,
							"translator": {
								"type": "TabularTranslator",
								"mappings": [
									{
										"source": {
											"name": "ID",
											"type": "String",
											"physicalType": "String"
										},
										"sink": {
											"name": "ID",
											"type": "Int32",
											"physicalType": "int"
										}
									},
									{
										"source": {
											"name": "Year",
											"type": "String",
											"physicalType": "String"
										},
										"sink": {
											"name": "Year",
											"type": "Int32",
											"physicalType": "int"
										}
									},
									{
										"source": {
											"name": "Date",
											"type": "String",
											"physicalType": "String"
										},
										"sink": {
											"name": "Date",
											"type": "DateTime",
											"physicalType": "date"
										}
									},
									{
										"source": {
											"name": "Stage",
											"type": "String",
											"physicalType": "String"
										},
										"sink": {
											"name": "Stage",
											"type": "String",
											"physicalType": "varchar"
										}
									},
									{
										"source": {
											"name": "Home Team",
											"type": "String",
											"physicalType": "String"
										},
										"sink": {
											"name": "Home_Team",
											"type": "String",
											"physicalType": "varchar"
										}
									},
									{
										"source": {
											"name": "Home Goals",
											"type": "String",
											"physicalType": "String"
										},
										"sink": {
											"name": "Home_Goals",
											"type": "Int32",
											"physicalType": "int"
										}
									},
									{
										"source": {
											"name": "Away Goals",
											"type": "String",
											"physicalType": "String"
										},
										"sink": {
											"name": "Away_Goals",
											"type": "Int32",
											"physicalType": "int"
										}
									},
									{
										"source": {
											"name": "Away Team",
											"type": "String",
											"physicalType": "String"
										},
										"sink": {
											"name": "Away_Team",
											"type": "String",
											"physicalType": "varchar"
										}
									},
									{
										"source": {
											"name": "Win Conditions",
											"type": "String",
											"physicalType": "String"
										},
										"sink": {
											"name": "Win_Conditions",
											"type": "String",
											"physicalType": "varchar"
										}
									},
									{
										"source": {
											"name": "Host Team",
											"type": "String",
											"physicalType": "String"
										},
										"sink": {
											"name": "Host_Team",
											"type": "Boolean",
											"physicalType": "bit"
										}
									}
								],
								"typeConversion": true,
								"typeConversionSettings": {
									"allowDataTruncation": true,
									"treatBooleanAsNumber": false
								}
							}
						},
						"inputs": [
							{
								"referenceName": "worldcupmatches",
								"type": "DatasetReference",
								"parameters": {}
							}
						],
						"outputs": [
							{
								"referenceName": "Worldcupmatches2",
								"type": "DatasetReference",
								"parameters": {}
							}
						]
					},
					{
						"name": "copy InternationalMatches to Stage",
						"type": "Copy",
						"dependsOn": [
							{
								"activity": "Copy worldcup matches to stage",
								"dependencyConditions": [
									"Succeeded"
								]
							}
						],
						"policy": {
							"timeout": "0.12:00:00",
							"retry": 0,
							"retryIntervalInSeconds": 30,
							"secureOutput": false,
							"secureInput": false
						},
						"userProperties": [],
						"typeProperties": {
							"source": {
								"type": "DelimitedTextSource",
								"storeSettings": {
									"type": "AzureBlobFSReadSettings",
									"recursive": true,
									"enablePartitionDiscovery": false
								},
								"formatSettings": {
									"type": "DelimitedTextReadSettings"
								}
							},
							"sink": {
								"type": "AzureSqlSink",
								"writeBehavior": "insert",
								"sqlWriterUseTableLock": false
							},
							"enableStaging": false,
							"translator": {
								"type": "TabularTranslator",
								"mappings": [
									{
										"source": {
											"name": "ID",
											"type": "String",
											"physicalType": "String"
										},
										"sink": {
											"name": "ID",
											"type": "Int32",
											"physicalType": "int"
										}
									},
									{
										"source": {
											"name": "Tournament",
											"type": "String",
											"physicalType": "String"
										},
										"sink": {
											"name": "Tournament",
											"type": "String",
											"physicalType": "varchar"
										}
									},
									{
										"source": {
											"name": "Date",
											"type": "String",
											"physicalType": "String"
										},
										"sink": {
											"name": "Date",
											"type": "DateTime",
											"physicalType": "date"
										}
									},
									{
										"source": {
											"name": "Home Team",
											"type": "String",
											"physicalType": "String"
										},
										"sink": {
											"name": "Home_Team",
											"type": "String",
											"physicalType": "varchar"
										}
									},
									{
										"source": {
											"name": "Home Goals",
											"type": "String",
											"physicalType": "String"
										},
										"sink": {
											"name": "Home_Goals",
											"type": "Int32",
											"physicalType": "int"
										}
									},
									{
										"source": {
											"name": "Away Goals",
											"type": "String",
											"physicalType": "String"
										},
										"sink": {
											"name": "Away_Goals",
											"type": "Int32",
											"physicalType": "int"
										}
									},
									{
										"source": {
											"name": "Away Team",
											"type": "String",
											"physicalType": "String"
										},
										"sink": {
											"name": "Away_Team",
											"type": "String",
											"physicalType": "varchar"
										}
									},
									{
										"source": {
											"name": "Win Conditions",
											"type": "String",
											"physicalType": "String"
										},
										"sink": {
											"name": "Win_Conditions",
											"type": "String",
											"physicalType": "varchar"
										}
									},
									{
										"source": {
											"name": "Home Stadium",
											"type": "String",
											"physicalType": "String"
										},
										"sink": {
											"name": "Home_Stadium",
											"type": "Boolean",
											"physicalType": "bit"
										}
									}
								],
								"typeConversion": true,
								"typeConversionSettings": {
									"allowDataTruncation": true,
									"treatBooleanAsNumber": false
								}
							}
						},
						"inputs": [
							{
								"referenceName": "InternationalMatches",
								"type": "DatasetReference",
								"parameters": {}
							}
						],
						"outputs": [
							{
								"referenceName": "internationalmatches_sql",
								"type": "DatasetReference",
								"parameters": {}
							}
						]
					},
					{
						"name": "Copy worldcup matches 2022 to stage",
						"type": "Copy",
						"dependsOn": [
							{
								"activity": "copy InternationalMatches to Stage",
								"dependencyConditions": [
									"Succeeded"
								]
							}
						],
						"policy": {
							"timeout": "0.12:00:00",
							"retry": 0,
							"retryIntervalInSeconds": 30,
							"secureOutput": false,
							"secureInput": false
						},
						"userProperties": [],
						"typeProperties": {
							"source": {
								"type": "DelimitedTextSource",
								"storeSettings": {
									"type": "AzureBlobFSReadSettings",
									"recursive": true,
									"enablePartitionDiscovery": false
								},
								"formatSettings": {
									"type": "DelimitedTextReadSettings"
								}
							},
							"sink": {
								"type": "AzureSqlSink",
								"writeBehavior": "insert",
								"sqlWriterUseTableLock": false
							},
							"enableStaging": false,
							"translator": {
								"type": "TabularTranslator",
								"mappings": [
									{
										"source": {
											"name": "ID",
											"type": "String",
											"physicalType": "String"
										},
										"sink": {
											"name": "ID",
											"type": "Int32",
											"physicalType": "int"
										}
									},
									{
										"source": {
											"name": "Year",
											"type": "String",
											"physicalType": "String"
										},
										"sink": {
											"name": "Year",
											"type": "Int32",
											"physicalType": "int"
										}
									},
									{
										"source": {
											"name": "Date",
											"type": "String",
											"physicalType": "String"
										},
										"sink": {
											"name": "Date",
											"type": "DateTime",
											"physicalType": "date"
										}
									},
									{
										"source": {
											"name": "Stage",
											"type": "String",
											"physicalType": "String"
										},
										"sink": {
											"name": "Stage",
											"type": "String",
											"physicalType": "varchar"
										}
									},
									{
										"source": {
											"name": "Home Team",
											"type": "String",
											"physicalType": "String"
										},
										"sink": {
											"name": "Home_Team",
											"type": "String",
											"physicalType": "varchar"
										}
									},
									{
										"source": {
											"name": "Away Team",
											"type": "String",
											"physicalType": "String"
										},
										"sink": {
											"name": "Away_Team",
											"type": "String",
											"physicalType": "varchar"
										}
									},
									{
										"source": {
											"name": "Host Team",
											"type": "String",
											"physicalType": "String"
										},
										"sink": {
											"name": "Host_Team",
											"type": "Boolean",
											"physicalType": "bit"
										}
									}
								],
								"typeConversion": true,
								"typeConversionSettings": {
									"allowDataTruncation": true,
									"treatBooleanAsNumber": false
								}
							}
						},
						"inputs": [
							{
								"referenceName": "worldcup_matches_2022",
								"type": "DatasetReference",
								"parameters": {}
							}
						],
						"outputs": [
							{
								"referenceName": "AzureSqlTable3",
								"type": "DatasetReference",
								"parameters": {}
							}
						]
					},
					{
						"name": "Copy worldcup squad 2022",
						"type": "Copy",
						"dependsOn": [
							{
								"activity": "Copy worldcup matches 2022 to stage",
								"dependencyConditions": [
									"Succeeded"
								]
							}
						],
						"policy": {
							"timeout": "0.12:00:00",
							"retry": 0,
							"retryIntervalInSeconds": 30,
							"secureOutput": false,
							"secureInput": false
						},
						"userProperties": [],
						"typeProperties": {
							"source": {
								"type": "DelimitedTextSource",
								"storeSettings": {
									"type": "AzureBlobFSReadSettings",
									"recursive": true,
									"enablePartitionDiscovery": false
								},
								"formatSettings": {
									"type": "DelimitedTextReadSettings"
								}
							},
							"sink": {
								"type": "AzureSqlSink",
								"writeBehavior": "insert",
								"sqlWriterUseTableLock": false
							},
							"enableStaging": false,
							"translator": {
								"type": "TabularTranslator",
								"mappings": [
									{
										"source": {
											"name": "ID",
											"type": "String",
											"physicalType": "String"
										},
										"sink": {
											"name": "ID",
											"type": "Int32",
											"physicalType": "int"
										}
									},
									{
										"source": {
											"name": "Team",
											"type": "String",
											"physicalType": "String"
										},
										"sink": {
											"name": "Team",
											"type": "String",
											"physicalType": "varchar"
										}
									},
									{
										"source": {
											"name": "Position",
											"type": "String",
											"physicalType": "String"
										},
										"sink": {
											"name": "Position",
											"type": "String",
											"physicalType": "varchar"
										}
									},
									{
										"source": {
											"name": "Player",
											"type": "String",
											"physicalType": "String"
										},
										"sink": {
											"name": "Player",
											"type": "String",
											"physicalType": "varchar"
										}
									},
									{
										"source": {
											"name": "Age",
											"type": "String",
											"physicalType": "String"
										},
										"sink": {
											"name": "Age",
											"type": "Int32",
											"physicalType": "int"
										}
									},
									{
										"source": {
											"name": "Caps",
											"type": "String",
											"physicalType": "String"
										},
										"sink": {
											"name": "Caps",
											"type": "Int32",
											"physicalType": "int"
										}
									},
									{
										"source": {
											"name": "Goals",
											"type": "String",
											"physicalType": "String"
										},
										"sink": {
											"name": "Goals",
											"type": "Int32",
											"physicalType": "int"
										}
									},
									{
										"source": {
											"name": "WC Goals",
											"type": "String",
											"physicalType": "String"
										},
										"sink": {
											"name": "WC_Goals",
											"type": "Int32",
											"physicalType": "int"
										}
									},
									{
										"source": {
											"name": "League",
											"type": "String",
											"physicalType": "String"
										},
										"sink": {
											"name": "League",
											"type": "String",
											"physicalType": "varchar"
										}
									},
									{
										"source": {
											"name": "Club",
											"type": "String",
											"physicalType": "String"
										},
										"sink": {
											"name": "Club",
											"type": "String",
											"physicalType": "varchar"
										}
									}
								],
								"typeConversion": true,
								"typeConversionSettings": {
									"allowDataTruncation": true,
									"treatBooleanAsNumber": false
								}
							}
						},
						"inputs": [
							{
								"referenceName": "worldcup_squad_2022",
								"type": "DatasetReference",
								"parameters": {}
							}
						],
						"outputs": [
							{
								"referenceName": "worldcup_squad_sql",
								"type": "DatasetReference",
								"parameters": {}
							}
						]
					},
					{
						"name": "Copy worldcup groups to stage",
						"type": "Copy",
						"dependsOn": [
							{
								"activity": "Copy worldcup squad 2022",
								"dependencyConditions": [
									"Succeeded"
								]
							}
						],
						"policy": {
							"timeout": "0.12:00:00",
							"retry": 0,
							"retryIntervalInSeconds": 30,
							"secureOutput": false,
							"secureInput": false
						},
						"userProperties": [],
						"typeProperties": {
							"source": {
								"type": "DelimitedTextSource",
								"storeSettings": {
									"type": "AzureBlobFSReadSettings",
									"recursive": true,
									"enablePartitionDiscovery": false
								},
								"formatSettings": {
									"type": "DelimitedTextReadSettings"
								}
							},
							"sink": {
								"type": "AzureSqlSink",
								"writeBehavior": "insert",
								"sqlWriterUseTableLock": false
							},
							"enableStaging": false,
							"translator": {
								"type": "TabularTranslator",
								"mappings": [
									{
										"source": {
											"name": "Group",
											"type": "String",
											"physicalType": "String"
										},
										"sink": {
											"name": "Groups",
											"type": "String",
											"physicalType": "varchar"
										}
									},
									{
										"source": {
											"name": "Team",
											"type": "String",
											"physicalType": "String"
										},
										"sink": {
											"name": "Team",
											"type": "String",
											"physicalType": "varchar"
										}
									},
									{
										"source": {
											"name": "FIFA Ranking",
											"type": "String",
											"physicalType": "String"
										},
										"sink": {
											"name": "FIFA_Ranking",
											"type": "Int32",
											"physicalType": "int"
										}
									}
								],
								"typeConversion": true,
								"typeConversionSettings": {
									"allowDataTruncation": true,
									"treatBooleanAsNumber": false
								}
							}
						},
						"inputs": [
							{
								"referenceName": "worldcup_group",
								"type": "DatasetReference",
								"parameters": {}
							}
						],
						"outputs": [
							{
								"referenceName": "worldcup_group_sql",
								"type": "DatasetReference",
								"parameters": {}
							}
						]
					}
				],
				"policy": {
					"elapsedTimeMetric": {},
					"cancelAfter": {}
				},
				"annotations": [],
				"lastPublishTime": "2023-08-07T10:46:11Z"
			},
			"dependsOn": [
				"[concat(variables('factoryId'), '/datasets/worldcupmatches')]",
				"[concat(variables('factoryId'), '/datasets/worldcup_matches_2022')]",
				"[concat(variables('factoryId'), '/datasets/worldcup_squad_2022')]",
				"[concat(variables('factoryId'), '/datasets/worldcup_squad_sql')]",
				"[concat(variables('factoryId'), '/datasets/worldcup_group_sql')]"
			]
		},
		{
			"name": "[concat(parameters('factoryName'), '/PizzaSalesTrigger')]",
			"type": "Microsoft.DataFactory/factories/triggers",
			"apiVersion": "2018-06-01",
			"properties": {
				"description": "PizzaSalesTrigger",
				"annotations": [],
				"runtimeState": "Started",
				"pipelines": [
					{
						"pipelineReference": {
							"referenceName": "PizzaSales",
							"type": "PipelineReference"
						},
						"parameters": {}
					}
				],
				"type": "ScheduleTrigger",
				"typeProperties": {
					"recurrence": {
						"frequency": "Minute",
						"interval": 15,
						"startTime": "2023-07-08T22:00:00",
						"endTime": "2023-07-08T22:30:20",
						"timeZone": "India Standard Time"
					}
				}
			},
			"dependsOn": [
				"[concat(variables('factoryId'), '/pipelines/PizzaSales')]"
			]
		}
	]
}